Mopidy_Dirble-1.1.2.dist-info/entry_points.txt
Mopidy_Dirble-1.1.2.dist-info/WHEEL
Mopidy_Dirble-1.1.2.dist-info/top_level.txt
Mopidy_Dirble-1.1.2.dist-info/METADATA
Mopidy_Dirble-1.1.2.dist-info/metadata.json
Mopidy_Dirble-1.1.2.dist-info/DESCRIPTION.rst
Mopidy_Dirble-1.1.2.dist-info/RECORD
mopidy_dirble/translator.py
mopidy_dirble/actor.py
mopidy_dirble/__init__.py
mopidy_dirble/client.py
mopidy_dirble/ext.conf
