Metadata-Version: 2.0
Name: Mopidy-Dirble
Version: 1.1.2
Summary: Mopidy extension for Dirble open radio directory
Home-page: https://github.com/mopidy/mopidy-dirble
Author: Thomas Adamcik
Author-email: thomas@adamcik.no
License: Apache License, Version 2.0
Platform: UNKNOWN
Classifier: Environment :: No Input/Output (Daemon)
Classifier: Intended Audience :: End Users/Desktop
Classifier: License :: OSI Approved :: Apache Software License
Classifier: Operating System :: OS Independent
Classifier: Programming Language :: Python :: 2
Classifier: Topic :: Multimedia :: Sound/Audio :: Players
Requires-Dist: setuptools
Requires-Dist: Mopidy (>=1.0)
Requires-Dist: Pykka (>=1.1)
Requires-Dist: pycountry
Requires-Dist: requests
